agentbrowser/__init__.py
agentbrowser/browser.py
agentbrowser/test.py
agentbrowser/test_async.py
agentbrowser-0.2.2.dist-info/LICENSE
agentbrowser-0.2.2.dist-info/METADATA
agentbrowser-0.2.2.dist-info/WHEEL
agentbrowser-0.2.2.dist-info/top_level.txt
agentbrowser-0.2.2.dist-info/RECORD
