Metadata-Version: 2.1
Name: agentbrowser
Version: 0.2.2
Summary: A browser for your agent, built on Playwright.
Home-page: https://github.com/AutonomousResearchGroup/agentbrowser
Author: Moon
Author-email: shawmakesmagic@gmail.com
License: MIT
Classifier: Development Status :: 2 - Pre-Alpha
Classifier: Intended Audience :: Science/Research
Classifier: License :: OSI Approved :: MIT License
Classifier: Operating System :: POSIX :: Linux
Classifier: Programming Language :: Python :: 3
Classifier: Operating System :: MacOS :: MacOS X
Classifier: Operating System :: Microsoft :: Windows
License-File: LICENSE
Requires-Dist: playwright
